ControlRoom/__init__.py
ControlRoom/classes.py
ControlRoom/fi2nspec.py
ControlRoom/fi_codes.py
ControlRoom/los.py
ControlRoom/los_cone.py
ControlRoom/los_nes.py
ControlRoom/mom2rz.py
ControlRoom/nes2phs.py
ControlRoom/plot_aug.py
ControlRoom/read_ascot.py
ControlRoom/read_equ.py
ControlRoom/read_toric.py
ControlRoom/tkhyper.py
ControlRoom/tot_nes.py
ControlRoom/units.py
ControlRoom-0.0.1.dist-info/LICENSE
ControlRoom-0.0.1.dist-info/METADATA
ControlRoom-0.0.1.dist-info/WHEEL
ControlRoom-0.0.1.dist-info/top_level.txt
ControlRoom-0.0.1.dist-info/RECORD
