Metadata-Version: 2.1
Name: ControlRoom
Version: 0.0.1
Summary: Interface to ControlRoom/GENESIS, calculating n/g emission spectra
Home-page: https://gitlab.mpcdf.mpg.de/git/ControlRoom
Author: Giovanni Tardini
Author-email: giovanni.tardini@ipp.mpg.de
License: UNKNOWN
Platform: UNKNOWN
Classifier: Programming Language :: Python :: 3
Classifier: License :: OSI Approved :: MIT License
Classifier: Operating System :: OS Independent
Requires-Python: >=2.6
License-File: LICENSE
